[
    {
        "count": 54,
        "todayUserMentions": "USCG!"
    },
    {
        "count": 43,
        "todayUserMentions": "POTUS"
    },
    {
        "count": 29,
        "todayUserMentions": "BarackObama!"
    },
    {
        "count": 28,
        "todayUserMentions": "USCG"
    },
    {
        "count": 14,
        "todayUserMentions": "CDCgov"
    },
    {
        "count": 9,
        "todayUserMentions": "BarackObama"
    },
    {
        "count": 8,
        "todayUserMentions": "RepCori"
    },
    {
        "count": 8,
        "todayUserMentions": "USCG."
    },
    {
        "count": 7,
        "todayUserMentions": "BarackObama."
    },
    {
        "count": 6,
        "todayUserMentions": "SecYellen"
    },
    {
        "count": 6,
        "todayUserMentions": "DHSgov"
    },
    {
        "count": 5,
        "todayUserMentions": "POTUS\u2019s"
    },
    {
        "count": 5,
        "todayUserMentions": "HouseDemocrats"
    },
    {
        "count": 5,
        "todayUserMentions": "ossoff"
    },
    {
        "count": 5,
        "todayUserMentions": "USCG,"
    },
    {
        "count": 5,
        "todayUserMentions": "SenateBanking"
    },
    {
        "count": 5,
        "todayUserMentions": "repjulialetlow"
    },
    {
        "count": 4,
        "todayUserMentions": "WhiteHouse"
    },
    {
        "count": 4,
        "todayUserMentions": "RepCori,"
    },
    {
        "count": 4,
        "todayUserMentions": ""
    },
    {
        "count": 4,
        "todayUserMentions": "SenMarkey"
    },
    {
        "count": 4,
        "todayUserMentions": "InvestAtlanta"
    },
    {
        "count": 4,
        "todayUserMentions": "JoeBiden"
    },
    {
        "count": 4,
        "todayUserMentions": "TeamUSA!"
    },
    {
        "count": 4,
        "todayUserMentions": "SenGaryPeters"
    },
    {
        "count": 4,
        "todayUserMentions": "SenateForeign"
    },
    {
        "count": 3,
        "todayUserMentions": "USProgressives"
    },
    {
        "count": 3,
        "todayUserMentions": "SenBlumenthal,"
    },
    {
        "count": 3,
        "todayUserMentions": "CTMirrorPaz"
    },
    {
        "count": 3,
        "todayUserMentions": "seanhannity"
    },
    {
        "count": 3,
        "todayUserMentions": "ChuckGrassley"
    },
    {
        "count": 3,
        "todayUserMentions": "TeamUSA"
    },
    {
        "count": 3,
        "todayUserMentions": "ChrisVanHollen"
    },
    {
        "count": 3,
        "todayUserMentions": "EnergyDems"
    },
    {
        "count": 3,
        "todayUserMentions": "NatlParkService"
    },
    {
        "count": 3,
        "todayUserMentions": "RepAOC,"
    },
    {
        "count": 3,
        "todayUserMentions": "CongressmanGT"
    },
    {
        "count": 3,
        "todayUserMentions": "SenBooker,"
    },
    {
        "count": 3,
        "todayUserMentions": "DCPoliceDept"
    },
    {
        "count": 3,
        "todayUserMentions": "SpeakerPelosi"
    },
    {
        "count": 3,
        "todayUserMentions": "AppropsDems"
    },
    {
        "count": 3,
        "todayUserMentions": "HouseDemocrats."
    },
    {
        "count": 3,
        "todayUserMentions": "shedd_aquarium"
    },
    {
        "count": 2,
        "todayUserMentions": "KennyBednarek"
    },
    {
        "count": 2,
        "todayUserMentions": "RepMcGovern"
    },
    {
        "count": 2,
        "todayUserMentions": "CindyMcCain"
    },
    {
        "count": 2,
        "todayUserMentions": "SenatorShaheen"
    },
    {
        "count": 2,
        "todayUserMentions": "RepMcKinley"
    },
    {
        "count": 2,
        "todayUserMentions": "cbsaustin"
    },
    {
        "count": 2,
        "todayUserMentions": "NIH"
    },
    {
        "count": 2,
        "todayUserMentions": "RepMcClintock"
    },
    {
        "count": 2,
        "todayUserMentions": "CoriBush,"
    },
    {
        "count": 2,
        "todayUserMentions": "FSCDems"
    },
    {
        "count": 2,
        "todayUserMentions": "SenMarkKelly\u2019s"
    },
    {
        "count": 2,
        "todayUserMentions": "RepMaxineWaters,"
    },
    {
        "count": 2,
        "todayUserMentions": "SecVilsack"
    },
    {
        "count": 2,
        "todayUserMentions": "GovRonDeSantis"
    },
    {
        "count": 2,
        "todayUserMentions": "Sen_JoeManchin"
    },
    {
        "count": 2,
        "todayUserMentions": "RepCori\u2019s"
    },
    {
        "count": 2,
        "todayUserMentions": "ENERGY's"
    },
    {
        "count": 2,
        "todayUserMentions": "washingtonpost"
    },
    {
        "count": 2,
        "todayUserMentions": "SBAGov"
    },
    {
        "count": 2,
        "todayUserMentions": "RepPfluger,"
    },
    {
        "count": 2,
        "todayUserMentions": "RepJayapal"
    },
    {
        "count": 2,
        "todayUserMentions": "TheLAA"
    },
    {
        "count": 2,
        "todayUserMentions": "RepJeffries!"
    },
    {
        "count": 2,
        "todayUserMentions": "Ilhan,"
    },
    {
        "count": 2,
        "todayUserMentions": "StateDept\u2019s"
    },
    {
        "count": 2,
        "todayUserMentions": "RepMaxineWaters."
    },
    {
        "count": 2,
        "todayUserMentions": "westerncaucus"
    },
    {
        "count": 2,
        "todayUserMentions": "SenWarren,"
    },
    {
        "count": 2,
        "todayUserMentions": "RepMarieNewman"
    },
    {
        "count": 2,
        "todayUserMentions": "KeishaBottoms"
    },
    {
        "count": 2,
        "todayUserMentions": "skylarsecurity"
    },
    {
        "count": 2,
        "todayUserMentions": "RepMaxineWaters"
    },
    {
        "count": 2,
        "todayUserMentions": "POTUS,"
    },
    {
        "count": 2,
        "todayUserMentions": "USCG!!"
    },
    {
        "count": 2,
        "todayUserMentions": "GOPLeader"
    },
    {
        "count": 2,
        "todayUserMentions": "SecBlinken"
    },
    {
        "count": 2,
        "todayUserMentions": "RepMcCaul,"
    },
    {
        "count": 2,
        "todayUserMentions": "AngeloChamber"
    },
    {
        "count": 2,
        "todayUserMentions": "MisesCaucusCT"
    },
    {
        "count": 2,
        "todayUserMentions": "UTPhysicians"
    },
    {
        "count": 2,
        "todayUserMentions": "USDA"
    },
    {
        "count": 2,
        "todayUserMentions": "Firebrand_Pod"
    },
    {
        "count": 2,
        "todayUserMentions": "USTreasury"
    },
    {
        "count": 2,
        "todayUserMentions": "CFPB\u2019s"
    },
    {
        "count": 2,
        "todayUserMentions": "RepHagedorn!"
    },
    {
        "count": 2,
        "todayUserMentions": "CDCgov\u2019s"
    },
    {
        "count": 2,
        "todayUserMentions": "WaysMeansCmte"
    },
    {
        "count": 2,
        "todayUserMentions": "CapitolPolice"
    },
    {
        "count": 2,
        "todayUserMentions": "TimKaine"
    },
    {
        "count": 2,
        "todayUserMentions": "FTC"
    },
    {
        "count": 2,
        "todayUserMentions": "SenatorWarnock"
    },
    {
        "count": 2,
        "todayUserMentions": "SenatorWicker"
    },
    {
        "count": 2,
        "todayUserMentions": "SenCortezMasto"
    },
    {
        "count": 2,
        "todayUserMentions": "SpeakerPelosi,"
    },
    {
        "count": 2,
        "todayUserMentions": "SenSchumer,"
    },
    {
        "count": 2,
        "todayUserMentions": "MartinHeinrich"
    },
    {
        "count": 2,
        "todayUserMentions": "SenMarkKelly!"
    },
    {
        "count": 2,
        "todayUserMentions": "POTUS'"
    },
    {
        "count": 2,
        "todayUserMentions": "politico"
    },
    {
        "count": 2,
        "todayUserMentions": "RepMcCaul"
    },
    {
        "count": 2,
        "todayUserMentions": "maziehirono"
    },
    {
        "count": 2,
        "todayUserMentions": "OSHA_DOL"
    },
    {
        "count": 2,
        "todayUserMentions": "SenSherrodBrown"
    },
    {
        "count": 2,
        "todayUserMentions": "SBAgov"
    },
    {
        "count": 2,
        "todayUserMentions": "PatrickMcHenry"
    },
    {
        "count": 2,
        "todayUserMentions": "DHSgov,"
    },
    {
        "count": 2,
        "todayUserMentions": "PaidLeaveforAll,"
    },
    {
        "count": 2,
        "todayUserMentions": "USNavy"
    },
    {
        "count": 2,
        "todayUserMentions": "PaidLeaveforAll"
    },
    {
        "count": 2,
        "todayUserMentions": "RepMcCaul:"
    },
    {
        "count": 2,
        "todayUserMentions": "SenGaryPeters\u2019"
    },
    {
        "count": 1,
        "todayUserMentions": "CFPB"
    },
    {
        "count": 1,
        "todayUserMentions": "Lancegooden"
    },
    {
        "count": 1,
        "todayUserMentions": "RepDonaldsPress"
    },
    {
        "count": 1,
        "todayUserMentions": "TXRandy14"
    },
    {
        "count": 1,
        "todayUserMentions": "RepKatCammack"
    },
    {
        "count": 1,
        "todayUserMentions": "RepCloudTX"
    },
    {
        "count": 1,
        "todayUserMentions": "RepNancyMace"
    },
    {
        "count": 1,
        "todayUserMentions": "RepBarryMoore"
    },
    {
        "count": 1,
        "todayUserMentions": "RepGrothman"
    },
    {
        "count": 1,
        "todayUserMentions": "RepBillJohnson"
    },
    {
        "count": 1,
        "todayUserMentions": "SenToddYoung"
    },
    {
        "count": 1,
        "todayUserMentions": "WarrenDavidson"
    },
    {
        "count": 1,
        "todayUserMentions": "RepCawthorn"
    },
    {
        "count": 1,
        "todayUserMentions": "RepBrianMast"
    },
    {
        "count": 1,
        "todayUserMentions": "RepGregSteube"
    },
    {
        "count": 1,
        "todayUserMentions": "FortCampbell\u2019s"
    },
    {
        "count": 1,
        "todayUserMentions": "CRKeeper"
    },
    {
        "count": 1,
        "todayUserMentions": "USCG's"
    },
    {
        "count": 1,
        "todayUserMentions": "USCG\u2019s"
    },
    {
        "count": 1,
        "todayUserMentions": "HASCRepublicans"
    },
    {
        "count": 1,
        "todayUserMentions": "HASCDemocrats"
    },
    {
        "count": 1,
        "todayUserMentions": "repjulialetlow."
    },
    {
        "count": 1,
        "todayUserMentions": "StoughtonPD"
    },
    {
        "count": 1,
        "todayUserMentions": "repjulialetlow's"
    },
    {
        "count": 1,
        "todayUserMentions": "SenatorLeahy"
    },
    {
        "count": 1,
        "todayUserMentions": "dallasnews:"
    },
    {
        "count": 1,
        "todayUserMentions": "CoryGardner"
    },
    {
        "count": 1,
        "todayUserMentions": "RepScottPerry"
    },
    {
        "count": 1,
        "todayUserMentions": "timkaine"
    },
    {
        "count": 1,
        "todayUserMentions": "mamazoecherotch"
    },
    {
        "count": 1,
        "todayUserMentions": "RepBrianBabin"
    },
    {
        "count": 1,
        "todayUserMentions": "FrankPallone,"
    },
    {
        "count": 1,
        "todayUserMentions": "mncorn,"
    },
    {
        "count": 1,
        "todayUserMentions": "rosadelauro,"
    },
    {
        "count": 1,
        "todayUserMentions": "MinnesotaPork,"
    },
    {
        "count": 1,
        "todayUserMentions": "MNFarmfest"
    },
    {
        "count": 1,
        "todayUserMentions": "dukeraleigh"
    },
    {
        "count": 1,
        "todayUserMentions": "SDSU"
    },
    {
        "count": 1,
        "todayUserMentions": "JackMcGrorySD"
    },
    {
        "count": 1,
        "todayUserMentions": "lapublichealth's"
    },
    {
        "count": 1,
        "todayUserMentions": "JBLM_PAO\u2019s"
    },
    {
        "count": 1,
        "todayUserMentions": "latimes."
    },
    {
        "count": 1,
        "todayUserMentions": "RepTedBudd"
    },
    {
        "count": 1,
        "todayUserMentions": "RepDanBishop"
    },
    {
        "count": 1,
        "todayUserMentions": "RepWesterman"
    },
    {
        "count": 1,
        "todayUserMentions": "replouiegohmert"
    },
    {
        "count": 1,
        "todayUserMentions": "RepJeffDuncan"
    },
    {
        "count": 1,
        "todayUserMentions": "SenWhitehouse"
    },
    {
        "count": 1,
        "todayUserMentions": "DesJarlaisTN04"
    },
    {
        "count": 1,
        "todayUserMentions": "RepMattGaetz"
    },
    {
        "count": 1,
        "todayUserMentions": "dcexaminer"
    },
    {
        "count": 1,
        "todayUserMentions": "RepHerrell"
    },
    {
        "count": 1,
        "todayUserMentions": "RepTenney"
    },
    {
        "count": 1,
        "todayUserMentions": "RepRonnyJackson"
    },
    {
        "count": 1,
        "todayUserMentions": "ConroeChamber"
    },
    {
        "count": 1,
        "todayUserMentions": "RepBlaine"
    },
    {
        "count": 1,
        "todayUserMentions": "HouseCommerce's"
    },
    {
        "count": 1,
        "todayUserMentions": "usairforce,"
    },
    {
        "count": 1,
        "todayUserMentions": "SecYellen,"
    },
    {
        "count": 1,
        "todayUserMentions": "NDSURTP"
    },
    {
        "count": 1,
        "todayUserMentions": "SecRaimondo,"
    },
    {
        "count": 1,
        "todayUserMentions": "RideSacRT"
    },
    {
        "count": 1,
        "todayUserMentions": "RepGallagher"
    },
    {
        "count": 1,
        "todayUserMentions": "GoSydGo,"
    },
    {
        "count": 1,
        "todayUserMentions": "RepKatiePorter's"
    },
    {
        "count": 1,
        "todayUserMentions": "OversightDems"
    },
    {
        "count": 1,
        "todayUserMentions": "Jim_Jordan"
    },
    {
        "count": 1,
        "todayUserMentions": "VP"
    },
    {
        "count": 1,
        "todayUserMentions": "OversightDems,"
    },
    {
        "count": 1,
        "todayUserMentions": "AP"
    },
    {
        "count": 1,
        "todayUserMentions": "ParkMaitland"
    },
    {
        "count": 1,
        "todayUserMentions": "32BJSEIU"
    },
    {
        "count": 1,
        "todayUserMentions": "SecMartyWalsh,"
    },
    {
        "count": 1,
        "todayUserMentions": "Caridad_Center"
    },
    {
        "count": 1,
        "todayUserMentions": "browardcenter"
    },
    {
        "count": 1,
        "todayUserMentions": "JECDems"
    },
    {
        "count": 1,
        "todayUserMentions": "NCAA's"
    },
    {
        "count": 1,
        "todayUserMentions": "RepTiffany"
    },
    {
        "count": 1,
        "todayUserMentions": "HouseAgDems"
    },
    {
        "count": 1,
        "todayUserMentions": "HouseAgGOP"
    },
    {
        "count": 1,
        "todayUserMentions": "NOAA"
    },
    {
        "count": 1,
        "todayUserMentions": "MontereyAq"
    },
    {
        "count": 1,
        "todayUserMentions": "USCoastGuard."
    },
    {
        "count": 1,
        "todayUserMentions": "usnews."
    },
    {
        "count": 1,
        "todayUserMentions": "futuristpharmd"
    },
    {
        "count": 1,
        "todayUserMentions": "journeyofeli"
    },
    {
        "count": 1,
        "todayUserMentions": "POTUS."
    },
    {
        "count": 1,
        "todayUserMentions": "APTA_Transit's"
    },
    {
        "count": 1,
        "todayUserMentions": "Boca_BlackBox,"
    },
    {
        "count": 1,
        "todayUserMentions": "OreFarmBureau"
    },
    {
        "count": 1,
        "todayUserMentions": "ColliervilleGov"
    },
    {
        "count": 1,
        "todayUserMentions": "BLMNational:"
    },
    {
        "count": 1,
        "todayUserMentions": "walittleleague"
    },
    {
        "count": 1,
        "todayUserMentions": "nytimes"
    },
    {
        "count": 1,
        "todayUserMentions": "RepMikeLevin"
    },
    {
        "count": 1,
        "todayUserMentions": "MomsDemand"
    },
    {
        "count": 1,
        "todayUserMentions": "Everytown"
    },
    {
        "count": 1,
        "todayUserMentions": "Rep_Clyde"
    },
    {
        "count": 1,
        "todayUserMentions": "MNSoyGrowers,"
    },
    {
        "count": 1,
        "todayUserMentions": "GregAbbott_TX"
    },
    {
        "count": 1,
        "todayUserMentions": "DanPatrick"
    },
    {
        "count": 1,
        "todayUserMentions": "CBSThisMorning"
    },
    {
        "count": 1,
        "todayUserMentions": "DavidBegnaud"
    },
    {
        "count": 1,
        "todayUserMentions": "colliervillepd."
    },
    {
        "count": 1,
        "todayUserMentions": "SoFlaOpinion"
    },
    {
        "count": 1,
        "todayUserMentions": "SecVetAffairs"
    },
    {
        "count": 1,
        "todayUserMentions": "MayorStanJoyner"
    },
    {
        "count": 1,
        "todayUserMentions": "TransportDems."
    },
    {
        "count": 1,
        "todayUserMentions": "bestselfwny's"
    },
    {
        "count": 1,
        "todayUserMentions": "GOPDoctors"
    },
    {
        "count": 1,
        "todayUserMentions": "JoaquinCastrotx"
    },
    {
        "count": 1,
        "todayUserMentions": "HHSGov"
    },
    {
        "count": 1,
        "todayUserMentions": "CongressmanHice"
    },
    {
        "count": 1,
        "todayUserMentions": "StCloudPDMN\u2019s"
    },
    {
        "count": 1,
        "todayUserMentions": "KNSI:"
    },
    {
        "count": 1,
        "todayUserMentions": "RepDavidTrone"
    },
    {
        "count": 1,
        "todayUserMentions": "courtfrerichs8"
    },
    {
        "count": 1,
        "todayUserMentions": "MNFarmBureau,"
    },
    {
        "count": 1,
        "todayUserMentions": "RepColinAllred's"
    },
    {
        "count": 1,
        "todayUserMentions": "AgCountry,"
    },
    {
        "count": 1,
        "todayUserMentions": "UnityCareNW,"
    },
    {
        "count": 1,
        "todayUserMentions": "HenricoPolice,"
    },
    {
        "count": 1,
        "todayUserMentions": "RepMcGovern\u2019s"
    },
    {
        "count": 1,
        "todayUserMentions": "RepBowman,"
    },
    {
        "count": 1,
        "todayUserMentions": "newtgingrich"
    },
    {
        "count": 1,
        "todayUserMentions": "IngrahamAngle"
    },
    {
        "count": 1,
        "todayUserMentions": "RepEdCase"
    },
    {
        "count": 1,
        "todayUserMentions": "Menlu_RI"
    },
    {
        "count": 1,
        "todayUserMentions": "ESSENCE"
    },
    {
        "count": 1,
        "todayUserMentions": "HeyBlueshirt"
    },
    {
        "count": 1,
        "todayUserMentions": "jawley12"
    },
    {
        "count": 1,
        "todayUserMentions": "DLydbyrd"
    },
    {
        "count": 1,
        "todayUserMentions": "eu_eeas"
    },
    {
        "count": 1,
        "todayUserMentions": "WhatcomCoHealth"
    },
    {
        "count": 1,
        "todayUserMentions": "ClintonHD76,"
    },
    {
        "count": 1,
        "todayUserMentions": "InterActionOrg"
    },
    {
        "count": 1,
        "todayUserMentions": "ToddPiro"
    },
    {
        "count": 1,
        "todayUserMentions": "jillianmele"
    },
    {
        "count": 1,
        "todayUserMentions": "RichardsonISD"
    },
    {
        "count": 1,
        "todayUserMentions": "BarackObama,"
    },
    {
        "count": 1,
        "todayUserMentions": "UAFS"
    },
    {
        "count": 1,
        "todayUserMentions": "UAFS,"
    },
    {
        "count": 1,
        "todayUserMentions": "jasoninthehouse"
    },
    {
        "count": 1,
        "todayUserMentions": "foxnewsradio"
    },
    {
        "count": 1,
        "todayUserMentions": "WhiteHouse,"
    },
    {
        "count": 1,
        "todayUserMentions": "uscg!"
    },
    {
        "count": 1,
        "todayUserMentions": "PhiladelphiaGov's"
    },
    {
        "count": 1,
        "todayUserMentions": "Mehdirhasan"
    },
    {
        "count": 1,
        "todayUserMentions": "NTIAgov\u2019s"
    },
    {
        "count": 1,
        "todayUserMentions": "HenricoFire."
    },
    {
        "count": 1,
        "todayUserMentions": "NLRB"
    },
    {
        "count": 1,
        "todayUserMentions": "JoeBiden?"
    },
    {
        "count": 1,
        "todayUserMentions": "SecretaryPete"
    },
    {
        "count": 1,
        "todayUserMentions": "RepGregoryMeeks:"
    },
    {
        "count": 1,
        "todayUserMentions": "PowerUSAID\u2019s"
    },
    {
        "count": 1,
        "todayUserMentions": "RepJimmyGomez,"
    },
    {
        "count": 1,
        "todayUserMentions": "WashFellowship"
    },
    {
        "count": 1,
        "todayUserMentions": "CaringAcrossGen"
    },
    {
        "count": 1,
        "todayUserMentions": "ZConine"
    },
    {
        "count": 1,
        "todayUserMentions": "domesticworkers"
    },
    {
        "count": 1,
        "todayUserMentions": "LamResearch"
    },
    {
        "count": 1,
        "todayUserMentions": "BISgov"
    },
    {
        "count": 1,
        "todayUserMentions": "Wade4Justice"
    },
    {
        "count": 1,
        "todayUserMentions": "GovSisolak"
    },
    {
        "count": 1,
        "todayUserMentions": "NYPD62Pct"
    },
    {
        "count": 1,
        "todayUserMentions": "RepJohnYarmuth"
    },
    {
        "count": 1,
        "todayUserMentions": "rosadelauro"
    },
    {
        "count": 1,
        "todayUserMentions": "SecBecerra,"
    },
    {
        "count": 1,
        "todayUserMentions": "guypbenson"
    },
    {
        "count": 1,
        "todayUserMentions": "jasonrantz"
    },
    {
        "count": 1,
        "todayUserMentions": "USDOT"
    },
    {
        "count": 1,
        "todayUserMentions": "thehill"
    },
    {
        "count": 1,
        "todayUserMentions": "HUDgov"
    },
    {
        "count": 1,
        "todayUserMentions": "NYPD24Pct."
    },
    {
        "count": 1,
        "todayUserMentions": "NYPD20Pct,"
    },
    {
        "count": 1,
        "todayUserMentions": "NYPDPSA4,"
    },
    {
        "count": 1,
        "todayUserMentions": "NYPD10Pct,"
    },
    {
        "count": 1,
        "todayUserMentions": "NYPD6Pct,"
    },
    {
        "count": 1,
        "todayUserMentions": "DOJ"
    },
    {
        "count": 1,
        "todayUserMentions": "GovAbbott\u2019s"
    },
    {
        "count": 1,
        "todayUserMentions": "DeptVetAffairs."
    },
    {
        "count": 1,
        "todayUserMentions": "USOCC"
    },
    {
        "count": 1,
        "todayUserMentions": "ZippyDuvall,"
    },
    {
        "count": 1,
        "todayUserMentions": "andrewrsorkin"
    },
    {
        "count": 1,
        "todayUserMentions": "RepMaxineWaters\u2019"
    },
    {
        "count": 1,
        "todayUserMentions": "SecYellen!"
    },
    {
        "count": 1,
        "todayUserMentions": "OversightDems\u2019"
    },
    {
        "count": 1,
        "todayUserMentions": "RepTedDeutch"
    },
    {
        "count": 1,
        "todayUserMentions": "MarkWarner"
    },
    {
        "count": 1,
        "todayUserMentions": "CAMcareWeCare"
    },
    {
        "count": 1,
        "todayUserMentions": "RepGregoryMeeks"
    },
    {
        "count": 1,
        "todayUserMentions": "CamdenCountyPD,"
    },
    {
        "count": 1,
        "todayUserMentions": "CityofCamdenGov's"
    },
    {
        "count": 1,
        "todayUserMentions": "AlabamaWildlife"
    },
    {
        "count": 1,
        "todayUserMentions": "indianhills'"
    },
    {
        "count": 1,
        "todayUserMentions": "RobinhoodApp,"
    },
    {
        "count": 1,
        "todayUserMentions": "BloombergTV"
    },
    {
        "count": 1,
        "todayUserMentions": "StateDept"
    },
    {
        "count": 1,
        "todayUserMentions": "IDF"
    },
    {
        "count": 1,
        "todayUserMentions": "USAID"
    },
    {
        "count": 1,
        "todayUserMentions": "SenWarren"
    },
    {
        "count": 1,
        "todayUserMentions": "AccessHealthCT"
    },
    {
        "count": 1,
        "todayUserMentions": "RepSpartz,"
    },
    {
        "count": 1,
        "todayUserMentions": "RepCarlos,"
    },
    {
        "count": 1,
        "todayUserMentions": "MarioDB,"
    },
    {
        "count": 1,
        "todayUserMentions": "RepMariaSalazar,"
    },
    {
        "count": 1,
        "todayUserMentions": "SenatorDurbin"
    },
    {
        "count": 1,
        "todayUserMentions": "Race_Imboden,"
    },
    {
        "count": 1,
        "todayUserMentions": "CompeerFinance"
    },
    {
        "count": 1,
        "todayUserMentions": "AURIcomm,"
    },
    {
        "count": 1,
        "todayUserMentions": "DeptVetAffairs"
    },
    {
        "count": 1,
        "todayUserMentions": "UMNExt,"
    },
    {
        "count": 1,
        "todayUserMentions": "RepJeffries."
    },
    {
        "count": 1,
        "todayUserMentions": "RepGwenMoore"
    },
    {
        "count": 1,
        "todayUserMentions": "RepRWilliams"
    },
    {
        "count": 1,
        "todayUserMentions": "RepChipRoy"
    },
    {
        "count": 1,
        "todayUserMentions": "RepRaulGrijalva"
    },
    {
        "count": 1,
        "todayUserMentions": "RepWesterman,"
    },
    {
        "count": 1,
        "todayUserMentions": "RepRubenGallego,"
    },
    {
        "count": 1,
        "todayUserMentions": "CMSGov:"
    },
    {
        "count": 1,
        "todayUserMentions": "labbielady"
    },
    {
        "count": 1,
        "todayUserMentions": "EndHungerCT"
    },
    {
        "count": 1,
        "todayUserMentions": "HouseDemocrats'"
    },
    {
        "count": 1,
        "todayUserMentions": "SecBecerra"
    },
    {
        "count": 1,
        "todayUserMentions": "RepEBJ"
    },
    {
        "count": 1,
        "todayUserMentions": "RepColinAllred"
    },
    {
        "count": 1,
        "todayUserMentions": "MNFarmfest!"
    },
    {
        "count": 1,
        "todayUserMentions": "RepMcCaul's"
    },
    {
        "count": 1,
        "todayUserMentions": "SenatorMenendez"
    },
    {
        "count": 1,
        "todayUserMentions": "mncorn\u2019s"
    },
    {
        "count": 1,
        "todayUserMentions": "SBAIsabel"
    },
    {
        "count": 1,
        "todayUserMentions": "NWArkCouncil\u2014bit.ly/3xTFlT6"
    },
    {
        "count": 1,
        "todayUserMentions": "DSenFloor."
    },
    {
        "count": 1,
        "todayUserMentions": "ADHPIO\u2014bit.ly/3wN6si2"
    },
    {
        "count": 1,
        "todayUserMentions": "Southfield_Gov"
    },
    {
        "count": 1,
        "todayUserMentions": "LawrenceTechU's"
    },
    {
        "count": 1,
        "todayUserMentions": "erykw19"
    },
    {
        "count": 1,
        "todayUserMentions": "USMNT"
    },
    {
        "count": 1,
        "todayUserMentions": "Sen_JoeManchin,"
    },
    {
        "count": 1,
        "todayUserMentions": "RepublicanStudy"
    },
    {
        "count": 1,
        "todayUserMentions": "RepJohnKatko,"
    },
    {
        "count": 1,
        "todayUserMentions": "seattletimes"
    },
    {
        "count": 1,
        "todayUserMentions": "JorArguello!"
    },
    {
        "count": 1,
        "todayUserMentions": "USCBO"
    },
    {
        "count": 1,
        "todayUserMentions": "MADDOnline"
    },
    {
        "count": 1,
        "todayUserMentions": "SFRCdems"
    },
    {
        "count": 1,
        "todayUserMentions": "EPWGOP"
    },
    {
        "count": 1,
        "todayUserMentions": "WVNews247:"
    },
    {
        "count": 1,
        "todayUserMentions": "_Kingben_"
    },
    {
        "count": 1,
        "todayUserMentions": "CoEvictionDef"
    },
    {
        "count": 1,
        "todayUserMentions": "CoriBush"
    },
    {
        "count": 1,
        "todayUserMentions": "SenOssoff"
    },
    {
        "count": 1,
        "todayUserMentions": "lazorlaze"
    },
    {
        "count": 1,
        "todayUserMentions": "emmabeancx"
    },
    {
        "count": 1,
        "todayUserMentions": "WSJOpinion"
    },
    {
        "count": 1,
        "todayUserMentions": "jasonrileywsj"
    },
    {
        "count": 1,
        "todayUserMentions": "CityofTLH"
    },
    {
        "count": 1,
        "todayUserMentions": "ConcernedVets"
    },
    {
        "count": 1,
        "todayUserMentions": "MiamiDadeCounty"
    },
    {
        "count": 1,
        "todayUserMentions": "IAGovernor"
    },
    {
        "count": 1,
        "todayUserMentions": "EPWcmte"
    },
    {
        "count": 1,
        "todayUserMentions": "LACaldwell,"
    },
    {
        "count": 1,
        "todayUserMentions": "SavannahLMaddox"
    },
    {
        "count": 1,
        "todayUserMentions": "EPWGOP,"
    },
    {
        "count": 1,
        "todayUserMentions": "ICEgov."
    },
    {
        "count": 1,
        "todayUserMentions": "SheriffEd_HCSO,"
    },
    {
        "count": 1,
        "todayUserMentions": "VarneyCo"
    },
    {
        "count": 1,
        "todayUserMentions": "alonsoleon4HD22"
    },
    {
        "count": 1,
        "todayUserMentions": "wlnsvey"
    },
    {
        "count": 1,
        "todayUserMentions": "WSJopinion:"
    },
    {
        "count": 1,
        "todayUserMentions": "NASA."
    },
    {
        "count": 1,
        "todayUserMentions": "GabbyGiffords"
    },
    {
        "count": 1,
        "todayUserMentions": "USCG!\ud83c\uddfa\ud83c\uddf8"
    },
    {
        "count": 1,
        "todayUserMentions": "JohnCornyn"
    },
    {
        "count": 1,
        "todayUserMentions": "GillibrandNY,"
    },
    {
        "count": 1,
        "todayUserMentions": "USTreasury\u2019s"
    },
    {
        "count": 1,
        "todayUserMentions": "nationalguardMS"
    },
    {
        "count": 1,
        "todayUserMentions": "feeonline"
    },
    {
        "count": 1,
        "todayUserMentions": "FinnertyUSA"
    },
    {
        "count": 1,
        "todayUserMentions": "Newsmax"
    },
    {
        "count": 1,
        "todayUserMentions": "WashTimes"
    },
    {
        "count": 1,
        "todayUserMentions": "sanjuanisnps."
    },
    {
        "count": 1,
        "todayUserMentions": "EbeysLandingNHR"
    },
    {
        "count": 1,
        "todayUserMentions": "RepFischbach"
    },
    {
        "count": 1,
        "todayUserMentions": "LCFoodBank"
    },
    {
        "count": 1,
        "todayUserMentions": "PFPAOfficial."
    },
    {
        "count": 1,
        "todayUserMentions": "SenTinaSmith"
    },
    {
        "count": 1,
        "todayUserMentions": "electcharles."
    },
    {
        "count": 1,
        "todayUserMentions": "DrewDarbyTX"
    },
    {
        "count": 1,
        "todayUserMentions": "WhirlpoolCorp\u2019s"
    },
    {
        "count": 1,
        "todayUserMentions": "MPShiels"
    },
    {
        "count": 1,
        "todayUserMentions": "mibigshow"
    },
    {
        "count": 1,
        "todayUserMentions": "FoxBusiness"
    },
    {
        "count": 1,
        "todayUserMentions": "MorningsMaria"
    },
    {
        "count": 1,
        "todayUserMentions": "MariaBartiromo"
    },
    {
        "count": 1,
        "todayUserMentions": "MNTeabagger"
    },
    {
        "count": 1,
        "todayUserMentions": "TomRoten."
    },
    {
        "count": 1,
        "todayUserMentions": "SBAgov."
    },
    {
        "count": 1,
        "todayUserMentions": "MayorGallego"
    },
    {
        "count": 1,
        "todayUserMentions": "FEMA's"
    },
    {
        "count": 1,
        "todayUserMentions": "ArkRazorbacks"
    },
    {
        "count": 1,
        "todayUserMentions": "MTGreenee"
    },
    {
        "count": 1,
        "todayUserMentions": "TaylorManson4"
    },
    {
        "count": 1,
        "todayUserMentions": "WhortWheet"
    },
    {
        "count": 1,
        "todayUserMentions": "RonWyden,"
    },
    {
        "count": 1,
        "todayUserMentions": "SenateDemocrats"
    },
    {
        "count": 1,
        "todayUserMentions": "columbiapdsc"
    },
    {
        "count": 1,
        "todayUserMentions": "JacksonLeeTX18"
    },
    {
        "count": 1,
        "todayUserMentions": "GovDirections"
    },
    {
        "count": 1,
        "todayUserMentions": "BLMNational"
    },
    {
        "count": 1,
        "todayUserMentions": "HeraldOped."
    },
    {
        "count": 1,
        "todayUserMentions": "HHSgov"
    },
    {
        "count": 1,
        "todayUserMentions": "CourtFrerichs8"
    },
    {
        "count": 1,
        "todayUserMentions": "GrassleyPress"
    },
    {
        "count": 1,
        "todayUserMentions": "TheROYALlife21"
    },
    {
        "count": 1,
        "todayUserMentions": "MayorSiddiqui,"
    },
    {
        "count": 1,
        "todayUserMentions": "RJScaringe"
    },
    {
        "count": 1,
        "todayUserMentions": "Rivian"
    },
    {
        "count": 1,
        "todayUserMentions": "mitchellreports"
    },
    {
        "count": 1,
        "todayUserMentions": "HeritageAction"
    },
    {
        "count": 1,
        "todayUserMentions": "SenatorRisch:"
    },
    {
        "count": 1,
        "todayUserMentions": "SenatorCardin"
    },
    {
        "count": 1,
        "todayUserMentions": "ChrisCoons"
    },
    {
        "count": 1,
        "todayUserMentions": "ChrisMurphyCT"
    },
    {
        "count": 1,
        "todayUserMentions": "SteveDaines"
    },
    {
        "count": 1,
        "todayUserMentions": "JimInhofe"
    },
    {
        "count": 1,
        "todayUserMentions": "SenJoniErnst,"
    },
    {
        "count": 1,
        "todayUserMentions": "SenSasse,"
    },
    {
        "count": 1,
        "todayUserMentions": "UofNH"
    },
    {
        "count": 1,
        "todayUserMentions": "club4growth"
    },
    {
        "count": 1,
        "todayUserMentions": "WPAFB"
    },
    {
        "count": 1,
        "todayUserMentions": "SenToomey"
    },
    {
        "count": 1,
        "todayUserMentions": "SenLummis"
    },
    {
        "count": 1,
        "todayUserMentions": "AFPhq"
    },
    {
        "count": 1,
        "todayUserMentions": "NCAA."
    },
    {
        "count": 1,
        "todayUserMentions": "SenJohnHoeven"
    },
    {
        "count": 1,
        "todayUserMentions": "teamUSA"
    },
    {
        "count": 1,
        "todayUserMentions": "weskitts22!"
    },
    {
        "count": 1,
        "todayUserMentions": "USD."
    },
    {
        "count": 1,
        "todayUserMentions": "RCrouserThrows."
    },
    {
        "count": 1,
        "todayUserMentions": "TexasTribune"
    },
    {
        "count": 1,
        "todayUserMentions": "Morning_Joe"
    },
    {
        "count": 1,
        "todayUserMentions": "MSNBC"
    },
    {
        "count": 1,
        "todayUserMentions": "OregonTF"
    },
    {
        "count": 1,
        "todayUserMentions": "DFADcoalition\u2019s"
    },
    {
        "count": 1,
        "todayUserMentions": "BankingGOP"
    },
    {
        "count": 1,
        "todayUserMentions": "CommerceDems"
    },
    {
        "count": 1,
        "todayUserMentions": "harrylitman"
    },
    {
        "count": 1,
        "todayUserMentions": "JudiciaryDems"
    },
    {
        "count": 1,
        "todayUserMentions": "EnergyDems,"
    },
    {
        "count": 1,
        "todayUserMentions": "RISD"
    },
    {
        "count": 1,
        "todayUserMentions": "linakhanFTC"
    },
    {
        "count": 1,
        "todayUserMentions": "SenMarkKelly,"
    },
    {
        "count": 1,
        "todayUserMentions": "SenMarkKelly's"
    },
    {
        "count": 1,
        "todayUserMentions": "GOPHELP!"
    },
    {
        "count": 1,
        "todayUserMentions": "SenSherrodBrown's"
    },
    {
        "count": 1,
        "todayUserMentions": "trailblazers"
    },
    {
        "count": 1,
        "todayUserMentions": "EnesKanter"
    },
    {
        "count": 1,
        "todayUserMentions": "SenAmyKlobuchar"
    },
    {
        "count": 1,
        "todayUserMentions": "SenJohnBarrasso"
    },
    {
        "count": 1,
        "todayUserMentions": "SenMarkKelly"
    },
    {
        "count": 1,
        "todayUserMentions": "WSJ,"
    },
    {
        "count": 1,
        "todayUserMentions": "Yair_Rosenberg's"
    },
    {
        "count": 1,
        "todayUserMentions": "CongressmanRaja"
    },
    {
        "count": 1,
        "todayUserMentions": "commercedems."
    },
    {
        "count": 1,
        "todayUserMentions": "CynthiaMLummis"
    },
    {
        "count": 1,
        "todayUserMentions": "giladerdan1"
    },
    {
        "count": 1,
        "todayUserMentions": "Cyber_Dot_Org"
    },
    {
        "count": 1,
        "todayUserMentions": "GirlScouts,"
    },
    {
        "count": 1,
        "todayUserMentions": "TeamUSA.\ud83e\udd47That\u2019s"
    },
    {
        "count": 1,
        "todayUserMentions": "RonWyden"
    },
    {
        "count": 1,
        "todayUserMentions": "PattyMurray,"
    },
    {
        "count": 1,
        "todayUserMentions": "LylesNoah"
    },
    {
        "count": 1,
        "todayUserMentions": "SenAlexPadilla"
    },
    {
        "count": 1,
        "todayUserMentions": "SenateGOP"
    },
    {
        "count": 1,
        "todayUserMentions": "TexasHDC"
    },
    {
        "count": 1,
        "todayUserMentions": "MarioDB"
    },
    {
        "count": 1,
        "todayUserMentions": "RaiseFuture,"
    },
    {
        "count": 1,
        "todayUserMentions": "TransportDems"
    },
    {
        "count": 1,
        "todayUserMentions": "RepZoeLofgren,"
    },
    {
        "count": 1,
        "todayUserMentions": "NCAA\u2019s"
    },
    {
        "count": 1,
        "todayUserMentions": "RepDebDingell's"
    },
    {
        "count": 1,
        "todayUserMentions": "goFAAR."
    },
    {
        "count": 1,
        "todayUserMentions": "beerinstitute,"
    },
    {
        "count": 1,
        "todayUserMentions": "DistilledSpirit,"
    },
    {
        "count": 1,
        "todayUserMentions": "foxandfriends"
    },
    {
        "count": 1,
        "todayUserMentions": "SenRickScott"
    },
    {
        "count": 1,
        "todayUserMentions": "SenatorLujan"
    },
    {
        "count": 1,
        "todayUserMentions": "RepDebDingell"
    },
    {
        "count": 1,
        "todayUserMentions": "Simone_Biles"
    },
    {
        "count": 1,
        "todayUserMentions": "HouseForeignGOP"
    },
    {
        "count": 1,
        "todayUserMentions": "RepBillFoster"
    },
    {
        "count": 1,
        "todayUserMentions": "RepCasten"
    },
    {
        "count": 1,
        "todayUserMentions": "RepRaulGrijalva."
    },
    {
        "count": 1,
        "todayUserMentions": "RepARmstrongND,"
    },
    {
        "count": 1,
        "todayUserMentions": "AbbyPalmerCox,"
    },
    {
        "count": 1,
        "todayUserMentions": "_MealsOnWheels"
    },
    {
        "count": 1,
        "todayUserMentions": "ncmchamber"
    },
    {
        "count": 1,
        "todayUserMentions": "RyanMelloPierc1."
    },
    {
        "count": 1,
        "todayUserMentions": "EvergreenStCol!"
    },
    {
        "count": 1,
        "todayUserMentions": "lucymcbath"
    },
    {
        "count": 1,
        "todayUserMentions": "eklementich"
    },
    {
        "count": 1,
        "todayUserMentions": "USAmbUN"
    },
    {
        "count": 1,
        "todayUserMentions": "Arkema_Inc"
    },
    {
        "count": 1,
        "todayUserMentions": "TiaChucha\u2019s"
    },
    {
        "count": 1,
        "todayUserMentions": "PalmerKrysta"
    },
    {
        "count": 1,
        "todayUserMentions": "FV_Chamber!"
    },
    {
        "count": 1,
        "todayUserMentions": "VillageFamily"
    },
    {
        "count": 1,
        "todayUserMentions": "jbletlow\u2019s"
    },
    {
        "count": 1,
        "todayUserMentions": "RepDonYoung"
    },
    {
        "count": 1,
        "todayUserMentions": "FTA_DOT"
    },
    {
        "count": 1,
        "todayUserMentions": "GovWhitmer"
    },
    {
        "count": 1,
        "todayUserMentions": "TheJusticeDept"
    },
    {
        "count": 1,
        "todayUserMentions": "USCG\u2693"
    },
    {
        "count": 1,
        "todayUserMentions": "FERC."
    },
    {
        "count": 1,
        "todayUserMentions": "Fergie"
    },
    {
        "count": 1,
        "todayUserMentions": "Fox32News"
    },
    {
        "count": 1,
        "todayUserMentions": "PoliticalEditor"
    },
    {
        "count": 1,
        "todayUserMentions": "FEMA,"
    },
    {
        "count": 1,
        "todayUserMentions": "MayorMikeDuggan,"
    },
    {
        "count": 1,
        "todayUserMentions": "RepHorsford"
    },
    {
        "count": 1,
        "todayUserMentions": "AlianzaProgress"
    },
    {
        "count": 1,
        "todayUserMentions": "32BJSEIU!"
    },
    {
        "count": 1,
        "todayUserMentions": "SecRaimondo"
    },
    {
        "count": 1,
        "todayUserMentions": "SecMartyWalsh"
    },
    {
        "count": 1,
        "todayUserMentions": "VP's"
    },
    {
        "count": 1,
        "todayUserMentions": "SenatorTimScott"
    },
    {
        "count": 1,
        "todayUserMentions": "JohnCornyn,"
    },
    {
        "count": 1,
        "todayUserMentions": "SenatorDurbin,"
    },
    {
        "count": 1,
        "todayUserMentions": "attorneycrump!"
    },
    {
        "count": 1,
        "todayUserMentions": "LowellNPS"
    },
    {
        "count": 1,
        "todayUserMentions": "NewDemCoalition"
    },
    {
        "count": 1,
        "todayUserMentions": "RepStefanik"
    },
    {
        "count": 1,
        "todayUserMentions": "housesciencegop"
    },
    {
        "count": 1,
        "todayUserMentions": "RepDustyJohnson\u2019s"
    },
    {
        "count": 1,
        "todayUserMentions": "monroeccc"
    },
    {
        "count": 1,
        "todayUserMentions": "NJHI_."
    },
    {
        "count": 1,
        "todayUserMentions": "centerffs,"
    },
    {
        "count": 1,
        "todayUserMentions": "Rutgers_Camden"
    },
    {
        "count": 1,
        "todayUserMentions": "RepBrianFitz"
    },
    {
        "count": 1,
        "todayUserMentions": "RepJeffries"
    },
    {
        "count": 1,
        "todayUserMentions": "kevinpmc"
    },
    {
        "count": 1,
        "todayUserMentions": "ACOG:"
    },
    {
        "count": 1,
        "todayUserMentions": "MonitorNews"
    },
    {
        "count": 1,
        "todayUserMentions": "TheAmandaGorman"
    },
    {
        "count": 1,
        "todayUserMentions": "GOPLeader\u2019s"
    },
    {
        "count": 1,
        "todayUserMentions": "ZippyDuvall"
    },
    {
        "count": 1,
        "todayUserMentions": "USCGLosAngeles"
    },
    {
        "count": 1,
        "todayUserMentions": "USCGAcademy"
    },
    {
        "count": 1,
        "todayUserMentions": "RepBowman"
    },
    {
        "count": 1,
        "todayUserMentions": "RepAOC"
    },
    {
        "count": 1,
        "todayUserMentions": "MNFFA"
    },
    {
        "count": 1,
        "todayUserMentions": "NYGovCuomo."
    },
    {
        "count": 1,
        "todayUserMentions": "FoxNews"
    },
    {
        "count": 1,
        "todayUserMentions": "AnheuserBusch"
    },
    {
        "count": 1,
        "todayUserMentions": "MensahTamStock"
    },
    {
        "count": 1,
        "todayUserMentions": "PhilaHsgAuthPHA"
    },
    {
        "count": 1,
        "todayUserMentions": "browardschools"
    },
    {
        "count": 1,
        "todayUserMentions": "RaceTrac"
    },
    {
        "count": 1,
        "todayUserMentions": "reedleycollege."
    },
    {
        "count": 1,
        "todayUserMentions": "foodbanktucson."
    },
    {
        "count": 1,
        "todayUserMentions": "NewsNationNow"
    },
    {
        "count": 1,
        "todayUserMentions": "TheDonlonReport"
    },
    {
        "count": 1,
        "todayUserMentions": "SunriseLAYouth"
    },
    {
        "count": 1,
        "todayUserMentions": "OIGatHHS"
    },
    {
        "count": 1,
        "todayUserMentions": "SecMayorkas"
    },
    {
        "count": 1,
        "todayUserMentions": "GovRonDeSantis."
    },
    {
        "count": 1,
        "todayUserMentions": "SenRandPaul\u2019s"
    },
    {
        "count": 1,
        "todayUserMentions": "Jstnorv10"
    },
    {
        "count": 1,
        "todayUserMentions": "RepPressley"
    },
    {
        "count": 1,
        "todayUserMentions": "RepMondaire,"
    },
    {
        "count": 1,
        "todayUserMentions": "SageFruit"
    },
    {
        "count": 1,
        "todayUserMentions": "RepSpartz"
    },
    {
        "count": 1,
        "todayUserMentions": "RepCicilline"
    },
    {
        "count": 1,
        "todayUserMentions": "MarkMeadows"
    },
    {
        "count": 1,
        "todayUserMentions": "KatieHeigl,"
    },
    {
        "count": 1,
        "todayUserMentions": "Spotify"
    },
    {
        "count": 1,
        "todayUserMentions": "Mayor_Keller,"
    },
    {
        "count": 1,
        "todayUserMentions": "RepNewhouse"
    },
    {
        "count": 1,
        "todayUserMentions": "CumberlandMDPD"
    },
    {
        "count": 1,
        "todayUserMentions": "WalnutCreekGov!"
    },
    {
        "count": 1,
        "todayUserMentions": "CA_Richmond"
    },
    {
        "count": 1,
        "todayUserMentions": "PBCDEM's"
    },
    {
        "count": 1,
        "todayUserMentions": "Robinhoodapp"
    },
    {
        "count": 1,
        "todayUserMentions": "athiiing,"
    },
    {
        "count": 1,
        "todayUserMentions": "bdflorsheim,"
    },
    {
        "count": 1,
        "todayUserMentions": "FairFightAction"
    },
    {
        "count": 1,
        "todayUserMentions": "SayWordMel"
    },
    {
        "count": 1,
        "todayUserMentions": "RepJudyChu"
    },
    {
        "count": 1,
        "todayUserMentions": "RepSylviaGarcia,"
    },
    {
        "count": 1,
        "todayUserMentions": "DorisMatsui,"
    },
    {
        "count": 1,
        "todayUserMentions": "VetAffairsDems"
    },
    {
        "count": 1,
        "todayUserMentions": "MARTAservice"
    },
    {
        "count": 1,
        "todayUserMentions": "NikemaWilliams"
    },
    {
        "count": 1,
        "todayUserMentions": "CEOMARTA"
    },
    {
        "count": 1,
        "todayUserMentions": "SenBooker"
    },
    {
        "count": 1,
        "todayUserMentions": "LinaKhanFTC"
    },
    {
        "count": 1,
        "todayUserMentions": "RepAdams"
    },
    {
        "count": 1,
        "todayUserMentions": "kfabnews"
    },
    {
        "count": 1,
        "todayUserMentions": "wto"
    },
    {
        "count": 1,
        "todayUserMentions": "YonkersYMCA"
    },
    {
        "count": 1,
        "todayUserMentions": "Westhab1981"
    },
    {
        "count": 1,
        "todayUserMentions": "EliseStefanik"
    },
    {
        "count": 1,
        "todayUserMentions": "ChangetheRef"
    },
    {
        "count": 1,
        "todayUserMentions": "PatriciaPadauy"
    },
    {
        "count": 1,
        "todayUserMentions": "ManuelOliver00"
    },
    {
        "count": 1,
        "todayUserMentions": "CapitolPolice,"
    },
    {
        "count": 1,
        "todayUserMentions": "Fred_MD_Police"
    },
    {
        "count": 1,
        "todayUserMentions": "mcpnews"
    },
    {
        "count": 1,
        "todayUserMentions": "GOPLeader's"
    }
]